{
	"type":"minecraft:simple_random_selector",
	"config":{
		"features":[
			{
				"placement":[],
				"feature":{
					"type":"dif:structure_feature",
					"config":{
						"structure":"minecraft:spawner_zombie_0",
						"random_rotation":true,
						"ignored_blocks": "minecraft:pink_stained_glass"
					}
				}
			},
			{
				"placement":[],
				"feature":{
					"type":"dif:structure_feature",
					"config":{
						"structure":"minecraft:spawner_zombie_1",
						"random_rotation":true,
						"ignored_blocks": "minecraft:pink_stained_glass"
					}
				}
			},
			{
				"placement":[],
				"feature":{
					"type":"dif:structure_feature",
					"config":{
						"structure":"minecraft:spawner_spider_0",
						"random_rotation":true,
						"ignored_blocks": "minecraft:pink_stained_glass"
					}
				}
			},
			{
				"placement":[],
				"feature":{
					"type":"dif:structure_feature",
					"config":{
						"structure":"minecraft:spawner_spider_1",
						"random_rotation":true,
						"ignored_blocks": "minecraft:pink_stained_glass"
					}
				}
			},
			{
				"placement":[],
				"feature":{
					"type":"dif:structure_feature",
					"config":{
						"structure":"minecraft:spawner_creeper_0",
						"random_rotation":true,
						"ignored_blocks": "minecraft:pink_stained_glass"
					}
				}
			},
			{
				"placement":[],
				"feature":{
					"type":"dif:structure_feature",
					"config":{
						"structure":"minecraft:spawner_creeper_1",
						"random_rotation":true,
						"ignored_blocks": "minecraft:pink_stained_glass"
					}
				}
			},
			{
				"placement":[],
				"feature":{
					"type":"dif:structure_feature",
					"config":{
						"structure":"minecraft:spawner_skeleton_0",
						"random_rotation":true,
						"ignored_blocks": "minecraft:pink_stained_glass"
					}
				}
			},
			{
				"placement":[],
				"feature":{
					"type":"dif:structure_feature",
					"config":{
						"structure":"minecraft:spawner_skeleton_1",
						"random_rotation":true,
						"ignored_blocks": "minecraft:pink_stained_glass"
					}
				}
			}
		]
	}
}